<?xml version="1.0"?>
<ArrayOfDialogueEditorNode xmlns:xsd="http://www.w3.org/2001/XMLSchema" xmlns:xsi="http://www.w3.org/2001/XMLSchema-instance">
  <DialogueEditorNode>
    <m_Rect>
      <x>143</x>
      <y>-16</y>
      <position>
        <x>143</x>
        <y>-16</y>
      </position>
      <center>
        <x>243</x>
        <y>9</y>
      </center>
      <min>
        <x>143</x>
        <y>-16</y>
      </min>
      <max>
        <x>343</x>
        <y>34</y>
      </max>
      <width>200</width>
      <height>50</height>
      <size>
        <x>200</x>
        <y>50</y>
      </size>
      <xMin>143</xMin>
      <yMin>-16</yMin>
      <xMax>343</xMax>
      <yMax>34</yMax>
    </m_Rect>
    <m_HasPrompts>true</m_HasPrompts>
    <m_InPoint>
      <m_ID>0fef9b4e-854b-40fc-80c9-a6fd2c341776</m_ID>
    </m_InPoint>
    <m_OutPoint>
      <m_ID>8e920c7c-a5bd-4e67-a2e5-109b7abd61c1</m_ID>
    </m_OutPoint>
    <m_Name>Ghost</m_Name>
    <m_Line>...You can see me?</m_Line>
    <Emotion>3</Emotion>
  </DialogueEditorNode>
  <DialogueEditorNode>
    <m_Rect>
      <x>427</x>
      <y>-11</y>
      <position>
        <x>427</x>
        <y>-11</y>
      </position>
      <center>
        <x>527</x>
        <y>14</y>
      </center>
      <min>
        <x>427</x>
        <y>-11</y>
      </min>
      <max>
        <x>627</x>
        <y>39</y>
      </max>
      <width>200</width>
      <height>50</height>
      <size>
        <x>200</x>
        <y>50</y>
      </size>
      <xMin>427</xMin>
      <yMin>-11</yMin>
      <xMax>627</xMax>
      <yMax>39</yMax>
    </m_Rect>
    <m_HasPrompts>false</m_HasPrompts>
    <m_InPoint>
      <m_ID>c3202de0-16b8-473f-a0a0-1abb42826388</m_ID>
    </m_InPoint>
    <m_OutPoint>
      <m_ID>c326a20c-9e3d-4f7e-a19f-fafc8506fa28</m_ID>
    </m_OutPoint>
    <m_Name>Ghost</m_Name>
    <m_Line>Oh... nobody has seen me in a long time.</m_Line>
    <Emotion>3</Emotion>
  </DialogueEditorNode>
  <DialogueEditorNode>
    <m_Rect>
      <x>674</x>
      <y>-4</y>
      <position>
        <x>674</x>
        <y>-4</y>
      </position>
      <center>
        <x>774</x>
        <y>21</y>
      </center>
      <min>
        <x>674</x>
        <y>-4</y>
      </min>
      <max>
        <x>874</x>
        <y>46</y>
      </max>
      <width>200</width>
      <height>50</height>
      <size>
        <x>200</x>
        <y>50</y>
      </size>
      <xMin>674</xMin>
      <yMin>-4</yMin>
      <xMax>874</xMax>
      <yMax>46</yMax>
    </m_Rect>
    <m_HasPrompts>true</m_HasPrompts>
    <m_InPoint>
      <m_ID>b77623aa-7239-4dbe-93ff-03ed08b0e6d8</m_ID>
    </m_InPoint>
    <m_OutPoint>
      <m_ID>fe03d4ec-05af-4cba-a5fc-e55dcd0d994d</m_ID>
    </m_OutPoint>
    <m_Name>Ghost</m_Name>
    <m_Line>I feel a bit unprepared. What is your name?</m_Line>
    <Emotion>3</Emotion>
  </DialogueEditorNode>
  <DialogueEditorNode>
    <m_Rect>
      <x>958</x>
      <y>0</y>
      <position>
        <x>958</x>
        <y>0</y>
      </position>
      <center>
        <x>1058</x>
        <y>25</y>
      </center>
      <min>
        <x>958</x>
        <y>0</y>
      </min>
      <max>
        <x>1158</x>
        <y>50</y>
      </max>
      <width>200</width>
      <height>50</height>
      <size>
        <x>200</x>
        <y>50</y>
      </size>
      <xMin>958</xMin>
      <yMin>0</yMin>
      <xMax>1158</xMax>
      <yMax>50</yMax>
    </m_Rect>
    <m_HasPrompts>false</m_HasPrompts>
    <m_InPoint>
      <m_ID>bf7243a7-f3f3-458f-bd2f-eb412c8e5ee5</m_ID>
    </m_InPoint>
    <m_OutPoint>
      <m_ID>b3be518c-4cfe-4a60-b604-6d356c074fad</m_ID>
    </m_OutPoint>
    <m_Name>Ghost</m_Name>
    <m_Line>Hermit? That's a lovely name.</m_Line>
    <Emotion>1</Emotion>
  </DialogueEditorNode>
  <DialogueEditorNode>
    <m_Rect>
      <x>1219</x>
      <y>2</y>
      <position>
        <x>1219</x>
        <y>2</y>
      </position>
      <center>
        <x>1319</x>
        <y>27</y>
      </center>
      <min>
        <x>1219</x>
        <y>2</y>
      </min>
      <max>
        <x>1419</x>
        <y>52</y>
      </max>
      <width>200</width>
      <height>50</height>
      <size>
        <x>200</x>
        <y>50</y>
      </size>
      <xMin>1219</xMin>
      <yMin>2</yMin>
      <xMax>1419</xMax>
      <yMax>52</yMax>
    </m_Rect>
    <m_HasPrompts>false</m_HasPrompts>
    <m_InPoint>
      <m_ID>88aa9a2e-b0bf-46c3-954d-d2fa15f0d2b5</m_ID>
    </m_InPoint>
    <m_OutPoint>
      <m_ID>936df275-2248-4e7f-9c8d-df58667176a2</m_ID>
    </m_OutPoint>
    <m_Name>Ghost</m_Name>
    <m_Line>I seem to have forgotten my name. I've forgotten quite a bit.</m_Line>
    <Emotion>3</Emotion>
  </DialogueEditorNode>
  <DialogueEditorNode>
    <m_Rect>
      <x>1466</x>
      <y>4</y>
      <position>
        <x>1466</x>
        <y>4</y>
      </position>
      <center>
        <x>1566</x>
        <y>29</y>
      </center>
      <min>
        <x>1466</x>
        <y>4</y>
      </min>
      <max>
        <x>1666</x>
        <y>54</y>
      </max>
      <width>200</width>
      <height>50</height>
      <size>
        <x>200</x>
        <y>50</y>
      </size>
      <xMin>1466</xMin>
      <yMin>4</yMin>
      <xMax>1666</xMax>
      <yMax>54</yMax>
    </m_Rect>
    <m_HasPrompts>true</m_HasPrompts>
    <m_InPoint>
      <m_ID>453aecf8-adc4-41b1-a00a-d27d113133b4</m_ID>
    </m_InPoint>
    <m_OutPoint>
      <m_ID>e6636e1b-d8dc-4e77-81ec-f13280eac2d5</m_ID>
    </m_OutPoint>
    <m_Name>Ghost</m_Name>
    <m_Line>Could we talk for a little longer? I feel... at ease with somebody else here.</m_Line>
    <Emotion>3</Emotion>
  </DialogueEditorNode>
  <DialogueEditorNode>
    <m_Rect>
      <x>1751</x>
      <y>-4</y>
      <position>
        <x>1751</x>
        <y>-4</y>
      </position>
      <center>
        <x>1851</x>
        <y>21</y>
      </center>
      <min>
        <x>1751</x>
        <y>-4</y>
      </min>
      <max>
        <x>1951</x>
        <y>46</y>
      </max>
      <width>200</width>
      <height>50</height>
      <size>
        <x>200</x>
        <y>50</y>
      </size>
      <xMin>1751</xMin>
      <yMin>-4</yMin>
      <xMax>1951</xMax>
      <yMax>46</yMax>
    </m_Rect>
    <m_HasPrompts>false</m_HasPrompts>
    <m_InPoint>
      <m_ID>f87e9fe5-ab34-442e-8f36-897ba1fb7550</m_ID>
    </m_InPoint>
    <m_OutPoint>
      <m_ID>efe147fe-b048-448e-af05-a5e64b8cc47a</m_ID>
    </m_OutPoint>
    <m_Name>Ghost</m_Name>
    <m_Line>Ah, I understand. If you change your mind, I will be here.</m_Line>
    <Emotion>3</Emotion>
  </DialogueEditorNode>
  <DialogueEditorNode>
    <m_Rect>
      <x>144</x>
      <y>271</y>
      <position>
        <x>144</x>
        <y>271</y>
      </position>
      <center>
        <x>244</x>
        <y>296</y>
      </center>
      <min>
        <x>144</x>
        <y>271</y>
      </min>
      <max>
        <x>344</x>
        <y>321</y>
      </max>
      <width>200</width>
      <height>50</height>
      <size>
        <x>200</x>
        <y>50</y>
      </size>
      <xMin>144</xMin>
      <yMin>271</yMin>
      <xMax>344</xMax>
      <yMax>321</yMax>
    </m_Rect>
    <m_HasPrompts>true</m_HasPrompts>
    <m_InPoint>
      <m_ID>0e724ce5-59c0-4656-86ef-a4e6963f0fb7</m_ID>
    </m_InPoint>
    <m_OutPoint>
      <m_ID>91ae9863-f8ba-489f-a7e6-f7fe2dbc9e6e</m_ID>
    </m_OutPoint>
    <m_Name>Ghost</m_Name>
    <m_Line>Oh, thank you!</m_Line>
    <Emotion>1</Emotion>
  </DialogueEditorNode>
  <DialogueEditorNode>
    <m_Rect>
      <x>428</x>
      <y>278</y>
      <position>
        <x>428</x>
        <y>278</y>
      </position>
      <center>
        <x>528</x>
        <y>303</y>
      </center>
      <min>
        <x>428</x>
        <y>278</y>
      </min>
      <max>
        <x>628</x>
        <y>328</y>
      </max>
      <width>200</width>
      <height>50</height>
      <size>
        <x>200</x>
        <y>50</y>
      </size>
      <xMin>428</xMin>
      <yMin>278</yMin>
      <xMax>628</xMax>
      <yMax>328</yMax>
    </m_Rect>
    <m_HasPrompts>false</m_HasPrompts>
    <m_InPoint>
      <m_ID>5dd2c1d9-c8c0-44a0-ad0f-b4ade03c4ca5</m_ID>
    </m_InPoint>
    <m_OutPoint>
      <m_ID>357265d8-6217-42e8-ab3b-e788b6c5bfc6</m_ID>
    </m_OutPoint>
    <m_Name>Ghost</m_Name>
    <m_Line>I can't remember much, just... feelings.</m_Line>
    <Emotion>3</Emotion>
  </DialogueEditorNode>
  <DialogueEditorNode>
    <m_Rect>
      <x>666</x>
      <y>288</y>
      <position>
        <x>666</x>
        <y>288</y>
      </position>
      <center>
        <x>766</x>
        <y>313</y>
      </center>
      <min>
        <x>666</x>
        <y>288</y>
      </min>
      <max>
        <x>866</x>
        <y>338</y>
      </max>
      <width>200</width>
      <height>50</height>
      <size>
        <x>200</x>
        <y>50</y>
      </size>
      <xMin>666</xMin>
      <yMin>288</yMin>
      <xMax>866</xMax>
      <yMax>338</yMax>
    </m_Rect>
    <m_HasPrompts>false</m_HasPrompts>
    <m_InPoint>
      <m_ID>14e09506-89c5-4e97-8032-5d74facf7aa4</m_ID>
    </m_InPoint>
    <m_OutPoint>
      <m_ID>5fd2c198-add2-4b91-bff3-4ffe886515bd</m_ID>
    </m_OutPoint>
    <m_Name>Ghost</m_Name>
    <m_Line>I remember a searing heat, hotter than anything I felt before.</m_Line>
    <Emotion>2</Emotion>
  </DialogueEditorNode>
  <DialogueEditorNode>
    <m_Rect>
      <x>953</x>
      <y>290</y>
      <position>
        <x>953</x>
        <y>290</y>
      </position>
      <center>
        <x>1053</x>
        <y>315</y>
      </center>
      <min>
        <x>953</x>
        <y>290</y>
      </min>
      <max>
        <x>1153</x>
        <y>340</y>
      </max>
      <width>200</width>
      <height>50</height>
      <size>
        <x>200</x>
        <y>50</y>
      </size>
      <xMin>953</xMin>
      <yMin>290</yMin>
      <xMax>1153</xMax>
      <yMax>340</yMax>
    </m_Rect>
    <m_HasPrompts>false</m_HasPrompts>
    <m_InPoint>
      <m_ID>c7623c23-11bb-4826-91ae-2d1563ebc046</m_ID>
    </m_InPoint>
    <m_OutPoint>
      <m_ID>5478172d-3bca-481e-b314-ee158f2e3f8e</m_ID>
    </m_OutPoint>
    <m_Name>Ghost</m_Name>
    <m_Line>I have a feeling of ease whenever I sit at this tree.</m_Line>
    <Emotion>0</Emotion>
  </DialogueEditorNode>
  <DialogueEditorNode>
    <m_Rect>
      <x>1201</x>
      <y>294</y>
      <position>
        <x>1201</x>
        <y>294</y>
      </position>
      <center>
        <x>1301</x>
        <y>319</y>
      </center>
      <min>
        <x>1201</x>
        <y>294</y>
      </min>
      <max>
        <x>1401</x>
        <y>344</y>
      </max>
      <width>200</width>
      <height>50</height>
      <size>
        <x>200</x>
        <y>50</y>
      </size>
      <xMin>1201</xMin>
      <yMin>294</yMin>
      <xMax>1401</xMax>
      <yMax>344</yMax>
    </m_Rect>
    <m_HasPrompts>false</m_HasPrompts>
    <m_InPoint>
      <m_ID>396ff212-924a-43b6-ab3a-8056935fd258</m_ID>
    </m_InPoint>
    <m_OutPoint>
      <m_ID>2e43a272-63f2-4db5-b7c1-3fd26e423ef5</m_ID>
    </m_OutPoint>
    <m_Name>Ghost</m_Name>
    <m_Line>And, more than anything, I have the burning desire to protect the man in that house.</m_Line>
    <Emotion>0</Emotion>
  </DialogueEditorNode>
  <DialogueEditorNode>
    <m_Rect>
      <x>1455</x>
      <y>305</y>
      <position>
        <x>1455</x>
        <y>305</y>
      </position>
      <center>
        <x>1555</x>
        <y>330</y>
      </center>
      <min>
        <x>1455</x>
        <y>305</y>
      </min>
      <max>
        <x>1655</x>
        <y>355</y>
      </max>
      <width>200</width>
      <height>50</height>
      <size>
        <x>200</x>
        <y>50</y>
      </size>
      <xMin>1455</xMin>
      <yMin>305</yMin>
      <xMax>1655</xMax>
      <yMax>355</yMax>
    </m_Rect>
    <m_HasPrompts>false</m_HasPrompts>
    <m_InPoint>
      <m_ID>24f48dc8-1426-403b-9b80-83bafb4ecd95</m_ID>
    </m_InPoint>
    <m_OutPoint>
      <m_ID>73396cef-1a43-4fc6-ba04-443c0169b5e8</m_ID>
    </m_OutPoint>
    <m_Name>Ghost</m_Name>
    <m_Line>I can't explain it, but saying it out loud to somebody makes me feel a lot better.</m_Line>
    <Emotion>0</Emotion>
  </DialogueEditorNode>
  <DialogueEditorNode>
    <m_Rect>
      <x>1706</x>
      <y>311</y>
      <position>
        <x>1706</x>
        <y>311</y>
      </position>
      <center>
        <x>1806</x>
        <y>336</y>
      </center>
      <min>
        <x>1706</x>
        <y>311</y>
      </min>
      <max>
        <x>1906</x>
        <y>361</y>
      </max>
      <width>200</width>
      <height>50</height>
      <size>
        <x>200</x>
        <y>50</y>
      </size>
      <xMin>1706</xMin>
      <yMin>311</yMin>
      <xMax>1906</xMax>
      <yMax>361</yMax>
    </m_Rect>
    <m_HasPrompts>false</m_HasPrompts>
    <m_InPoint>
      <m_ID>3d84d656-6910-44d8-ba99-4bfecc565b76</m_ID>
    </m_InPoint>
    <m_OutPoint>
      <m_ID>9b929dc2-555b-4f91-aae2-088167b3bd17</m_ID>
    </m_OutPoint>
    <m_Name>Ghost</m_Name>
    <m_Line>Perhaps with time, I'll figure everything out. I haven't been... like this for very long.</m_Line>
    <Emotion>0</Emotion>
  </DialogueEditorNode>
  <DialogueEditorNode>
    <m_Rect>
      <x>1973</x>
      <y>327</y>
      <position>
        <x>1973</x>
        <y>327</y>
      </position>
      <center>
        <x>2073</x>
        <y>352</y>
      </center>
      <min>
        <x>1973</x>
        <y>327</y>
      </min>
      <max>
        <x>2173</x>
        <y>377</y>
      </max>
      <width>200</width>
      <height>50</height>
      <size>
        <x>200</x>
        <y>50</y>
      </size>
      <xMin>1973</xMin>
      <yMin>327</yMin>
      <xMax>2173</xMax>
      <yMax>377</yMax>
    </m_Rect>
    <m_HasPrompts>false</m_HasPrompts>
    <m_InPoint>
      <m_ID>8a31408e-80db-4164-bc0d-8076552c8e1a</m_ID>
    </m_InPoint>
    <m_OutPoint>
      <m_ID>9c43b898-a0bb-4e0b-b567-ad955d7e9f7b</m_ID>
    </m_OutPoint>
    <m_Name>Ghost</m_Name>
    <m_Line>Thank you for listening to me. It eased a lot of my sadness.</m_Line>
    <Emotion>0</Emotion>
  </DialogueEditorNode>
  <DialogueEditorNode>
    <m_Rect>
      <x>2229</x>
      <y>330</y>
      <position>
        <x>2229</x>
        <y>330</y>
      </position>
      <center>
        <x>2329</x>
        <y>355</y>
      </center>
      <min>
        <x>2229</x>
        <y>330</y>
      </min>
      <max>
        <x>2429</x>
        <y>380</y>
      </max>
      <width>200</width>
      <height>50</height>
      <size>
        <x>200</x>
        <y>50</y>
      </size>
      <xMin>2229</xMin>
      <yMin>330</yMin>
      <xMax>2429</xMax>
      <yMax>380</yMax>
    </m_Rect>
    <m_HasPrompts>false</m_HasPrompts>
    <m_InPoint>
      <m_ID>89b48b0c-a497-4a9c-a8f9-123f1483e0ea</m_ID>
    </m_InPoint>
    <m_OutPoint>
      <m_ID>10a7cc04-c48f-4074-8bf1-19a617147dbc</m_ID>
    </m_OutPoint>
    <m_Name>Ghost</m_Name>
    <m_Line>I hope you come back and visit again.</m_Line>
    <Emotion>1</Emotion>
  </DialogueEditorNode>
</ArrayOfDialogueEditorNode>